[
  {
    "id": 1,
    "name": "Abduvali ",
    "username": "abduvali",
    "password": "48392",
    "image": "Abduvali.jpg",
    "level": "OK",
    "months": {
      "2025-08": { "davomat": 6, "uy_vazifa": 0, "tasks": 83, "jarima": 57 },
      "2025-09": { "davomat": 100, "uy_vazifa": 25, "tasks": 652, "jarima": 633 }
    }
  },
  {
    "id": 2,
    "name": "Elshodbek ",
    "username": "elshodbek",
    "password": "75021",
    "image": "Elshodbek.jpg",
    "level": "OK",
    "months": {
      "2025-08": { "davomat": 6, "uy_vazifa": 0, "tasks": 68, "jarima": 53 },
      "2025-09": { "davomat": 70, "uy_vazifa": 65, "tasks": 466, "jarima": 393 }
    }
  },
  {
    "id": 3,
    "name": "Ibrohimjon",
    "username": "ibrohimjon",
    "password": "12946",
    "image": "Ibrohimjon.jpg",
    "level": "OK",
    "months": {
      "2025-08": { "davomat": 6, "uy_vazifa": 0, "tasks": 78, "jarima": 78 },
      "2025-09": { "davomat": 110, "uy_vazifa": 35, "tasks": 411, "jarima": 458 }
    }
  },
  {
    "id": 4,
    "name": "Ziyodullo ",
    "username": "ziyodullo",
    "password": "67385",
    "image": "Ziyodulloh.jpg",
    "level": "OK",
    "months": {
      "2025-08": { "davomat": 6, "uy_vazifa": 0, "tasks": 80, "jarima": 38 },
      "2025-09": { "davomat": 70, "uy_vazifa": 25, "tasks": 514, "jarima": 373 }
    }
  },
  {
    "id": 5,
    "name": "Elnurbek",
    "username": "elnurbek",
    "password": "30417",
    "image": "Elnurbek.jpg",
    "level": "OK",
    "months": {
      "2025-08": { "davomat": 6, "uy_vazifa": 0, "tasks": 88, "jarima": 51 },
      "2025-09": { "davomat": 90, "uy_vazifa": 35, "tasks": 125, "jarima": 528 }
    }
  },
  {
    "id": 6,
    "name": "Sanjarbek",
    "username": "sanjarbek",
    "password": "89234",
    "image": "Sanjarbek.jpg",
    "level": "OK",
    "months": {
      "2025-08": { "davomat": 6, "uy_vazifa": 0, "tasks": 101, "jarima": 56 },
      "2025-09": { "davomat": 30, "uy_vazifa": 10, "tasks": 337, "jarima": 363 }
    }
  },
  {
    "id": 7,
    "name": "Behruzbek",
    "username": "behruzbek",
    "password": "52678",
    "image": "Behruzbek.jpg",
    "level": "OK",
    "months": {
      "2025-08": { "davomat": 6, "uy_vazifa": 0, "tasks": 82, "jarima": 46 },
      "2025-09": { "davomat": 80, "uy_vazifa": 45, "tasks": 371, "jarima": 378 }
    }
  },
  {
    "id": 8,
    "name": "Yahyobek",
    "username": "yahyobek",
    "password": "94103",
    "image": "Yahyobek.jpg",
    "level": "OK",
    "months": {
      "2025-08": { "davomat": 6, "uy_vazifa": 0, "tasks": 68, "jarima": 29 },
      "2025-09": { "davomat": 120, "uy_vazifa": 30, "tasks": 138, "jarima": 528 }
    }
  }
]


